{"any":["System","System."],"any.System":["Linq","Linq.","Private","Private.","Reflection","Reflection.","Xml","Xml."],"any.System.Linq":["Expressions"],"any.System.Private":["DataContractSerialization"],"any.System.Reflection":["DispatchProxy"],"any.System.Xml":["XmlSerializer"],"aot":["System","System."],"aot.System":["Linq","Linq.","Private","Private.","Reflection","Reflection.","Xml","Xml."],"aot.System.Linq":["Expressions"],"aot.System.Private":["DataContractSerialization"],"aot.System.Reflection":["DispatchProxy"],"aot.System.Xml":["XmlSerializer"],"centos":["7","7."],"centos.7":["1-x64","1-x64."],"centos.7.1-x64":["Microsoft","Microsoft."],"centos.7.1-x64.Microsoft":["NETCore","NETCore."],"centos.7.1-x64.Microsoft.NETCore":["ConsoleHost","Runtime","Runtime.","TestHost"],"centos.7.1-x64.Microsoft.NETCore.Runtime":["CoreCLR"],"linux":["System","System."],"linux.System":["Diagnostics","Diagnostics.","IO","IO.","Net","Net.","Runtime","Runtime.","Security","Security."],"linux.System.Diagnostics":["Process"],"linux.System.IO":["Compression","Compression.","FileSystem","FileSystem.","MemoryMappedFiles"],"linux.System.IO.Compression":["ZipFile"],"linux.System.IO.FileSystem":["DriveInfo","Watcher"],"linux.System.Net":["Http","NameResolution","NetworkInformation","Sockets"],"linux.System.Runtime":["Extensions","InteropServices","InteropServices."],"linux.System.Runtime.InteropServices":["RuntimeInformation"],"linux.System.Security":["Cryptography","Cryptography."],"linux.System.Security.Cryptography":["Algorithms"],"osx":["10","10.","System","System."],"osx.10":["10","10-x64","10-x64.","10."],"osx.10.10":["System","System."],"osx.10.10.System":["Diagnostics","Diagnostics.","IO","IO.","Net","Net.","Runtime","Runtime.","Security","Security."],"osx.10.10.System.Diagnostics":["Process"],"osx.10.10.System.IO":["Compression","Compression.","FileSystem","FileSystem.","MemoryMappedFiles"],"osx.10.10.System.IO.Compression":["ZipFile"],"osx.10.10.System.IO.FileSystem":["DriveInfo","Watcher"],"osx.10.10.System.Net":["Http","NameResolution","NetworkInformation","Primitives","Sockets"],"osx.10.10.System.Runtime":["Extensions","InteropServices","InteropServices."],"osx.10.10.System.Runtime.InteropServices":["RuntimeInformation"],"osx.10.10.System.Security":["Cryptography","Cryptography."],"osx.10.10.System.Security.Cryptography":["Algorithms"],"osx.10.10-x64":["Microsoft","Microsoft."],"osx.10.10-x64.Microsoft":["NETCore","NETCore."],"osx.10.10-x64.Microsoft.NETCore":["ConsoleHost","Runtime","Runtime.","TestHost"],"osx.10.10-x64.Microsoft.NETCore.Runtime":["CoreCLR"],"osx.System":["Diagnostics","Diagnostics.","IO","IO.","Net","Net.","Runtime","Runtime."],"osx.System.Diagnostics":["Process"],"osx.System.IO":["Compression","Compression.","FileSystem","FileSystem.","MemoryMappedFiles"],"osx.System.IO.Compression":["ZipFile"],"osx.System.IO.FileSystem":["DriveInfo","Watcher"],"osx.System.Net":["Http"],"osx.System.Runtime":["Extensions","InteropServices","InteropServices."],"osx.System.Runtime.InteropServices":["RuntimeInformation"],"ubuntu":["14","14."],"ubuntu.14":["04-x64","04-x64."],"ubuntu.14.04-x64":["Microsoft","Microsoft."],"ubuntu.14.04-x64.Microsoft":["NETCore","NETCore."],"ubuntu.14.04-x64.Microsoft.NETCore":["ConsoleHost","Runtime","Runtime.","TestHost"],"ubuntu.14.04-x64.Microsoft.NETCore.Runtime":["CoreCLR"],"unix":["Microsoft","Microsoft.","System","System."],"unix.Microsoft":["Win32","Win32."],"unix.Microsoft.Win32":["Primitives"],"unix.System":["Console","Data","Data.","Diagnostics","Diagnostics.","Globalization","Globalization.","IO","IO.","Net","Net.","Private","Private.","Security","Security.","Text","Text.","Threading"],"unix.System.Data":["SqlClient"],"unix.System.Diagnostics":["Debug","FileVersionInfo","TraceSource"],"unix.System.Globalization":["Extensions"],"unix.System.IO":["Compression","Pipes"],"unix.System.Net":["Primitives","Requests","Security","WebSockets","WebSockets."],"unix.System.Net.WebSockets":["Client"],"unix.System.Private":["Uri"],"unix.System.Security":["Cryptography","Cryptography."],"unix.System.Security.Cryptography":["Encoding","X509Certificates"],"unix.System.Text":["Encoding","Encoding."],"unix.System.Text.Encoding":["CodePages"],"win":["System","System."],"win.System":["Runtime","Runtime.","Text","Text."],"win.System.Runtime":["InteropServices","InteropServices."],"win.System.Runtime.InteropServices":["RuntimeInformation"],"win.System.Text":["Encoding","Encoding."],"win.System.Text.Encoding":["CodePages"],"win7":["Microsoft","Microsoft.","System","System."],"win7.Microsoft":["Win32","Win32."],"win7.Microsoft.Win32":["Primitives"],"win7.System":["Console","Data","Data.","Diagnostics","Diagnostics.","Globalization","Globalization.","IO","IO.","Net","Net.","Private","Private.","Runtime","Runtime.","Security","Security.","Text","Text.","Threading"],"win7.System.Data":["SqlClient"],"win7.System.Diagnostics":["Debug","FileVersionInfo","Process","TraceSource"],"win7.System.Globalization":["Extensions"],"win7.System.IO":["Compression","Compression.","FileSystem","FileSystem.","MemoryMappedFiles","Pipes"],"win7.System.IO.Compression":["ZipFile"],"win7.System.IO.FileSystem":["DriveInfo","Watcher"],"win7.System.Net":["Http","NameResolution","NetworkInformation","Primitives","Requests","Security","Sockets","WebSockets","WebSockets."],"win7.System.Net.WebSockets":["Client"],"win7.System.Private":["Uri"],"win7.System.Runtime":["Extensions","InteropServices","InteropServices."],"win7.System.Runtime.InteropServices":["RuntimeInformation"],"win7.System.Security":["Cryptography","Cryptography."],"win7.System.Security.Cryptography":["Algorithms","Encoding","X509Certificates"],"win7.System.Text":["Encoding","Encoding."],"win7.System.Text.Encoding":["CodePages"],"win7-arm":["Microsoft","Microsoft.","System","System."],"win7-arm.Microsoft":["NETCore","NETCore."],"win7-arm.Microsoft.NETCore":["ConsoleHost","TestHost"],"win7-arm.System":["IO","IO."],"win7-arm.System.IO":["Compression","Compression."],"win7-arm.System.IO.Compression":["clrcompression"],"win7-x64":["Microsoft","Microsoft.","System","System."],"win7-x64.Microsoft":["NETCore","NETCore."],"win7-x64.Microsoft.NETCore":["ConsoleHost","Runtime","Runtime.","TestHost","Windows","Windows."],"win7-x64.Microsoft.NETCore.Runtime":["CoreCLR"],"win7-x64.Microsoft.NETCore.Windows":["ApiSets"],"win7-x64.System":["Data","Data.","IO","IO."],"win7-x64.System.Data":["SqlClient","SqlClient."],"win7-x64.System.Data.SqlClient":["sni"],"win7-x64.System.IO":["Compression","Compression."],"win7-x64.System.IO.Compression":["clrcompression"],"win7-x86":["Microsoft","Microsoft.","System","System."],"win7-x86.Microsoft":["NETCore","NETCore."],"win7-x86.Microsoft.NETCore":["ConsoleHost","Runtime","Runtime.","TestHost","Windows","Windows."],"win7-x86.Microsoft.NETCore.Runtime":["CoreCLR"],"win7-x86.Microsoft.NETCore.Windows":["ApiSets"],"win7-x86.System":["Data","Data.","IO","IO."],"win7-x86.System.Data":["SqlClient","SqlClient."],"win7-x86.System.Data.SqlClient":["sni"],"win7-x86.System.IO":["Compression","Compression."],"win7-x86.System.IO.Compression":["clrcompression"],"win8-arm":["Microsoft","Microsoft."],"win8-arm.Microsoft":["NETCore","NETCore."],"win8-arm.Microsoft.NETCore":["Runtime","Runtime."],"win8-arm.Microsoft.NETCore.Runtime":["CoreCLR"],"_keys":["any.","aot.","centos.","linux.","osx.","ubuntu.","unix.","win.","win7-arm.","win7-x64.","win7-x86.","win7.","win8-arm."]}